nac_yaml/__init__.py
nac_yaml/ansible_vault.py
nac_yaml/yaml.py
nac_yaml-1.1.1.dist-info/METADATA
nac_yaml-1.1.1.dist-info/WHEEL
nac_yaml-1.1.1.dist-info/licenses/LICENSE
nac_yaml-1.1.1.dist-info/RECORD
